[{"actual": 0, "prob": 0.0}, {"actual": 7, "prob": 0.0}, {"actual": 1, "prob": 0.0}, {"actual": 6, "prob": 0.0}, {"actual": 1, "prob": 0.0}, {"actual": 6, "prob": 0.0}, {"actual": 8, "prob": 0.0}, {"actual": 2, "prob": 0.0}, {"actual": 4, "prob": 0.0}, {"actual": 8, "prob": 0.0}, {"actual": 9, "prob": 3.849896074825665e-06}, {"actual": 7, "prob": 0.0}, {"actual": 9, "prob": 2.3675883592427967e-26}, {"actual": 6, "prob": 0.0}, {"actual": 2, "prob": 0.0}, {"actual": 7, "prob": 0.0}, {"actual": 9, "prob": 2.3980475591378614e-11}, {"actual": 4, "prob": 0.0}, {"actual": 4, "prob": 0.0}, {"actual": 2, "prob": 0.0}, {"actual": 7, "prob": 0.0}, {"actual": 0, "prob": 0.0}, {"actual": 3, "prob": 1.0}, {"actual": 2, "prob": 0.0}, {"actual": 0, "prob": 0.0}, {"actual": 4, "prob": 0.0}, {"actual": 6, "prob": 0.0}, {"actual": 5, "prob": 3.089112637576751e-30}, {"actual": 9, "prob": 3.7397615215474015e-25}, {"actual": 2, "prob": 0.0}, {"actual": 7, "prob": 0.0}, {"actual": 5, "prob": 1.401298464324817e-44}, {"actual": 6, "prob": 0.0}, {"actual": 0, "prob": 0.0}, {"actual": 3, "prob": 1.0}, {"actual": 8, "prob": 0.0}, {"actual": 7, "prob": 0.0}, {"actual": 2, "prob": 0.0}, {"actual": 3, "prob": 1.0}, {"actual": 2, "prob": 0.0}, {"actual": 9, "prob": 2.322581146504965e-13}, {"actual": 0, "prob": 0.0}, {"actual": 8, "prob": 0.0}, {"actual": 4, "prob": 0.0}, {"actual": 1, "prob": 0.0}, {"actual": 6, "prob": 0.0}, {"actual": 4, "prob": 0.0}, {"actual": 4, "prob": 0.0}, {"actual": 1, "prob": 0.0}, {"actual": 1, "prob": 0.0}, {"actual": 3, "prob": 1.0}, {"actual": 6, "prob": 0.0}, {"actual": 3, "prob": 1.0}, {"actual": 7, "prob": 0.0}, {"actual": 5, "prob": 5.304857231757208e-34}, {"actual": 3, "prob": 1.0}, {"actual": 1, "prob": 0.0}, {"actual": 3, "prob": 1.0}, {"actual": 1, "prob": 0.0}, {"actual": 1, "prob": 0.0}, {"actual": 3, "prob": 1.0}, {"actual": 7, "prob": 0.0}, {"actual": 9, "prob": 6.514068003370407e-19}, {"actual": 0, "prob": 0.0}, {"actual": 5, "prob": 0.0}, {"actual": 8, "prob": 0.0}, {"actual": 8, "prob": 0.0}, {"actual": 5, "prob": 4.9631840594090994e-29}, {"actual": 7, "prob": 0.0}, {"actual": 4, "prob": 0.0}, {"actual": 1, "prob": 0.0}, {"actual": 0, "prob": 0.0}, {"actual": 9, "prob": 3.833447337342477e-09}, {"actual": 5, "prob": 0.0}, {"actual": 8, "prob": 0.0}, {"actual": 2, "prob": 0.0}, {"actual": 1, "prob": 0.0}, {"actual": 6, "prob": 0.0}, {"actual": 1, "prob": 0.0}, {"actual": 4, "prob": 0.0}, {"actual": 0, "prob": 0.0}, {"actual": 4, "prob": 0.0}, {"actual": 9, "prob": 2.479901558356725e-14}, {"actual": 6, "prob": 0.0}, {"actual": 7, "prob": 0.0}, {"actual": 1, "prob": 0.0}, {"actual": 4, "prob": 0.0}, {"actual": 1, "prob": 0.0}, {"actual": 6, "prob": 0.0}, {"actual": 4, "prob": 0.0}, {"actual": 9, "prob": 1.746462870155785e-11}, {"actual": 7, "prob": 0.0}, {"actual": 0, "prob": 0.0}, {"actual": 5, "prob": 0.0}, {"actual": 5, "prob": 0.0}, {"actual": 9, "prob": 1.7371662918916342e-12}, {"actual": 2, "prob": 0.0}, {"actual": 6, "prob": 0.0}, {"actual": 3, "prob": 1.0}, {"actual": 5, "prob": 0.0}, {"actual": 6, "prob": 0.0}, {"actual": 4, "prob": 0.0}, {"actual": 0, "prob": 0.0}, {"actual": 7, "prob": 0.0}, {"actual": 8, "prob": 0.0}, {"actual": 5, "prob": 1.8511090114925835e-35}, {"actual": 3, "prob": 1.0}, {"actual": 8, "prob": 0.0}, {"actual": 9, "prob": 4.67859795350023e-09}, {"actual": 7, "prob": 0.0}, {"actual": 3, "prob": 1.0}, {"actual": 9, "prob": 7.960290204778175e-10}, {"actual": 3, "prob": 1.0}, {"actual": 3, "prob": 1.0}, {"actual": 0, "prob": 0.0}, {"actual": 6, "prob": 0.0}, {"actual": 2, "prob": 0.0}, {"actual": 5, "prob": 3.292645014608666e-40}, {"actual": 3, "prob": 1.0}, {"actual": 9, "prob": 1.4937653978336352e-12}, {"actual": 6, "prob": 0.0}, {"actual": 1, "prob": 0.0}, {"actual": 2, "prob": 0.0}, {"actual": 9, "prob": 5.029112543075698e-12}, {"actual": 7, "prob": 0.0}, {"actual": 9, "prob": 1.6648090891968614e-11}, {"actual": 6, "prob": 0.0}, {"actual": 0, "prob": 0.0}, {"actual": 4, "prob": 0.0}, {"actual": 3, "prob": 1.0}, {"actual": 8, "prob": 0.0}, {"actual": 2, "prob": 0.0}, {"actual": 4, "prob": 0.0}, {"actual": 3, "prob": 1.0}, {"actual": 0, "prob": 0.0}, {"actual": 5, "prob": 5.605193857299268e-44}, {"actual": 2, "prob": 0.0}, {"actual": 1, "prob": 0.0}, {"actual": 6, "prob": 0.0}, {"actual": 3, "prob": 1.0}, {"actual": 5, "prob": 0.0}, {"actual": 2, "prob": 0.0}, {"actual": 0, "prob": 0.0}, {"actual": 4, "prob": 0.0}, {"actual": 8, "prob": 0.0}, {"actual": 1, "prob": 0.0}, {"actual": 7, "prob": 0.0}, {"actual": 6, "prob": 0.0}, {"actual": 6, "prob": 0.0}, {"actual": 3, "prob": 1.0}, {"actual": 7, "prob": 0.0}, {"actual": 2, "prob": 0.0}, {"actual": 2, "prob": 0.0}, {"actual": 3, "prob": 1.0}, {"actual": 7, "prob": 0.0}, {"actual": 9, "prob": 2.109480938452396e-13}, {"actual": 1, "prob": 0.0}, {"actual": 0, "prob": 0.0}, {"actual": 5, "prob": 5.033201864814619e-34}, {"actual": 7, "prob": 0.0}, {"actual": 0, "prob": 0.0}, {"actual": 2, "prob": 0.0}, {"actual": 3, "prob": 1.0}, {"actual": 8, "prob": 0.0}, {"actual": 4, "prob": 0.0}, {"actual": 8, "prob": 0.0}, {"actual": 6, "prob": 0.0}, {"actual": 5, "prob": 0.0}, {"actual": 5, "prob": 3.637835273116584e-39}, {"actual": 0, "prob": 0.0}, {"actual": 9, "prob": 1.8627568931783856e-10}, {"actual": 8, "prob": 0.0}, {"actual": 1, "prob": 0.0}, {"actual": 2, "prob": 0.0}, {"actual": 7, "prob": 0.0}, {"actual": 7, "prob": 0.0}, {"actual": 3, "prob": 1.0}, {"actual": 0, "prob": 0.0}, {"actual": 6, "prob": 0.0}, {"actual": 9, "prob": 3.219973387317415e-14}, {"actual": 7, "prob": 0.0}, {"actual": 7, "prob": 0.0}, {"actual": 1, "prob": 0.0}, {"actual": 2, "prob": 0.0}, {"actual": 5, "prob": 2.2562189986061648e-37}, {"actual": 0, "prob": 0.0}, {"actual": 0, "prob": 0.0}, {"actual": 8, "prob": 0.0}, {"actual": 7, "prob": 0.0}, {"actual": 2, "prob": 0.0}, {"actual": 2, "prob": 0.0}, {"actual": 5, "prob": 0.0}, {"actual": 7, "prob": 0.0}, {"actual": 5, "prob": 0.0}, {"actual": 6, "prob": 0.0}, {"actual": 7, "prob": 0.0}, {"actual": 6, "prob": 0.0}, {"actual": 6, "prob": 0.0}, {"actual": 4, "prob": 0.0}, {"actual": 3, "prob": 1.0}, {"actual": 4, "prob": 0.0}, {"actual": 4, "prob": 0.0}, {"actual": 8, "prob": 0.0}, {"actual": 2, "prob": 0.0}, {"actual": 0, "prob": 0.0}, {"actual": 5, "prob": 4.989338876771312e-38}, {"actual": 2, "prob": 0.0}, {"actual": 4, "prob": 0.0}, {"actual": 4, "prob": 0.0}, {"actual": 4, "prob": 0.0}, {"actual": 0, "prob": 0.0}, {"actual": 5, "prob": 4.29469770421441e-32}, {"actual": 5, "prob": 0.0}, {"actual": 7, "prob": 0.0}, {"actual": 9, "prob": 5.676495037909568e-11}, {"actual": 9, "prob": 3.8837455895322694e-15}, {"actual": 9, "prob": 1.746462870155785e-11}, {"actual": 5, "prob": 5.664485149506271e-35}, {"actual": 9, "prob": 9.572424103376775e-11}, {"actual": 4, "prob": 0.0}, {"actual": 3, "prob": 1.0}, {"actual": 4, "prob": 0.0}, {"actual": 9, "prob": 6.327619761492542e-09}, {"actual": 0, "prob": 0.0}, {"actual": 0, "prob": 0.0}, {"actual": 0, "prob": 0.0}, {"actual": 2, "prob": 0.0}, {"actual": 7, "prob": 0.0}, {"actual": 1, "prob": 0.0}, {"actual": 0, "prob": 0.0}, {"actual": 0, "prob": 0.0}, {"actual": 3, "prob": 1.0}, {"actual": 8, "prob": 0.0}, {"actual": 6, "prob": 0.0}, {"actual": 4, "prob": 0.0}, {"actual": 3, "prob": 1.0}, {"actual": 0, "prob": 0.0}, {"actual": 5, "prob": 2.462439525097944e-32}, {"actual": 4, "prob": 0.0}, {"actual": 5, "prob": 0.0}, {"actual": 1, "prob": 0.0}, {"actual": 6, "prob": 0.0}, {"actual": 4, "prob": 0.0}, {"actual": 8, "prob": 0.0}, {"actual": 9, "prob": 2.960686695807624e-10}, {"actual": 6, "prob": 0.0}, {"actual": 9, "prob": 6.538371510877994e-10}, {"actual": 9, "prob": 1.2714035553529346e-12}, {"actual": 8, "prob": 0.0}, {"actual": 8, "prob": 0.0}, {"actual": 7, "prob": 0.0}, {"actual": 4, "prob": 0.0}, {"actual": 9, "prob": 8.83070743265546e-13}, {"actual": 2, "prob": 0.0}, {"actual": 6, "prob": 0.0}, {"actual": 2, "prob": 0.0}, {"actual": 7, "prob": 0.0}, {"actual": 9, "prob": 1.2714035553529346e-12}, {"actual": 6, "prob": 0.0}, {"actual": 8, "prob": 0.0}, {"actual": 4, "prob": 0.0}, {"actual": 2, "prob": 0.0}, {"actual": 1, "prob": 0.0}, {"actual": 2, "prob": 0.0}, {"actual": 7, "prob": 0.0}, {"actual": 6, "prob": 0.0}, {"actual": 9, "prob": 1.2639538135491977e-16}, {"actual": 9, "prob": 2.4198287817966957e-09}, {"actual": 3, "prob": 1.0}, {"actual": 6, "prob": 0.0}, {"actual": 4, "prob": 0.0}, {"actual": 6, "prob": 0.0}, {"actual": 7, "prob": 0.0}, {"actual": 0, "prob": 0.0}, {"actual": 1, "prob": 0.0}, {"actual": 7, "prob": 0.0}, {"actual": 8, "prob": 0.0}, {"actual": 3, "prob": 1.0}, {"actual": 3, "prob": 1.0}, {"actual": 8, "prob": 0.0}, {"actual": 8, "prob": 0.0}, {"actual": 4, "prob": 0.0}, {"actual": 2, "prob": 0.0}, {"actual": 8, "prob": 0.0}, {"actual": 2, "prob": 0.0}, {"actual": 7, "prob": 0.0}, {"actual": 6, "prob": 0.0}, {"actual": 4, "prob": 0.0}, {"actual": 9, "prob": 1.730165344326906e-09}, {"actual": 7, "prob": 0.0}, {"actual": 8, "prob": 0.0}, {"actual": 1, "prob": 0.0}, {"actual": 8, "prob": 0.0}, {"actual": 5, "prob": 0.0}, {"actual": 9, "prob": 9.415036733708178e-18}, {"actual": 1, "prob": 0.0}, {"actual": 7, "prob": 0.0}, {"actual": 5, "prob": 1.4583006015720522e-18}, {"actual": 6, "prob": 0.0}, {"actual": 4, "prob": 0.0}, {"actual": 1, "prob": 0.0}, {"actual": 9, "prob": 1.0565229247028185e-11}, {"actual": 8, "prob": 0.0}, {"actual": 5, "prob": 5.352960133720801e-42}, {"actual": 3, "prob": 1.0}, {"actual": 7, "prob": 0.0}, {"actual": 5, "prob": 3.4489915261247803e-32}, {"actual": 7, "prob": 0.0}, {"actual": 0, "prob": 0.0}, {"actual": 9, "prob": 2.566929376187217e-16}, {"actual": 3, "prob": 1.0}, {"actual": 3, "prob": 1.0}, {"actual": 9, "prob": 4.429125523373184e-13}, {"actual": 1, "prob": 0.0}, {"actual": 2, "prob": 0.0}, {"actual": 3, "prob": 1.0}, {"actual": 5, "prob": 3.75547988439051e-43}, {"actual": 2, "prob": 0.0}, {"actual": 0, "prob": 0.0}, {"actual": 3, "prob": 1.0}, {"actual": 7, "prob": 0.0}, {"actual": 0, "prob": 0.0}, {"actual": 4, "prob": 0.0}, {"actual": 9, "prob": 2.415860220206234e-11}, {"actual": 0, "prob": 0.0}, {"actual": 5, "prob": 0.0}, {"actual": 3, "prob": 1.0}, {"actual": 5, "prob": 8.419501586697803e-22}, {"actual": 4, "prob": 0.0}, {"actual": 2, "prob": 0.0}, {"actual": 7, "prob": 0.0}, {"actual": 6, "prob": 0.0}, {"actual": 1, "prob": 0.0}, {"actual": 7, "prob": 0.0}, {"actual": 7, "prob": 0.0}, {"actual": 7, "prob": 0.0}, {"actual": 1, "prob": 0.0}, {"actual": 4, "prob": 0.0}, {"actual": 0, "prob": 0.0}, {"actual": 1, "prob": 0.0}, {"actual": 2, "prob": 0.0}, {"actual": 1, "prob": 0.0}, {"actual": 8, "prob": 0.0}, {"actual": 7, "prob": 0.0}, {"actual": 8, "prob": 0.0}, {"actual": 9, "prob": 8.940878593044488e-11}, {"actual": 8, "prob": 0.0}, {"actual": 0, "prob": 0.0}, {"actual": 7, "prob": 0.0}, {"actual": 7, "prob": 0.0}, {"actual": 2, "prob": 0.0}, {"actual": 8, "prob": 0.0}, {"actual": 4, "prob": 0.0}, {"actual": 1, "prob": 0.0}, {"actual": 7, "prob": 0.0}, {"actual": 3, "prob": 1.0}, {"actual": 8, "prob": 0.0}, {"actual": 5, "prob": 0.0}, {"actual": 8, "prob": 0.0}, {"actual": 0, "prob": 0.0}, {"actual": 7, "prob": 0.0}, {"actual": 0, "prob": 0.0}, {"actual": 1, "prob": 0.0}, {"actual": 0, "prob": 0.0}, {"actual": 0, "prob": 0.0}, {"actual": 8, "prob": 0.0}, {"actual": 5, "prob": 3.923635700109488e-44}, {"actual": 8, "prob": 0.0}, {"actual": 5, "prob": 0.0}, {"actual": 9, "prob": 2.7807469660245943e-09}, {"actual": 6, "prob": 0.0}, {"actual": 4, "prob": 0.0}, {"actual": 8, "prob": 0.0}, {"actual": 1, "prob": 0.0}, {"actual": 3, "prob": 1.0}, {"actual": 3, "prob": 1.0}, {"actual": 5, "prob": 1.5566464120798663e-40}, {"actual": 6, "prob": 0.0}, {"actual": 7, "prob": 0.0}, {"actual": 9, "prob": 3.831613845650672e-12}, {"actual": 0, "prob": 0.0}, {"actual": 0, "prob": 0.0}, {"actual": 2, "prob": 0.0}, {"actual": 9, "prob": 3.790500899270022e-12}, {"actual": 4, "prob": 0.0}, {"actual": 0, "prob": 0.0}, {"actual": 3, "prob": 1.0}, {"actual": 1, "prob": 0.0}, {"actual": 3, "prob": 1.0}, {"actual": 6, "prob": 0.0}, {"actual": 3, "prob": 1.0}, {"actual": 2, "prob": 0.0}, {"actual": 2, "prob": 0.0}, {"actual": 2, "prob": 0.0}, {"actual": 4, "prob": 0.0}, {"actual": 2, "prob": 0.0}, {"actual": 6, "prob": 0.0}, {"actual": 1, "prob": 0.0}, {"actual": 2, "prob": 0.0}, {"actual": 5, "prob": 2.532510662635669e-40}, {"actual": 1, "prob": 0.0}, {"actual": 6, "prob": 0.0}, {"actual": 8, "prob": 0.0}, {"actual": 8, "prob": 0.0}, {"actual": 0, "prob": 0.0}, {"actual": 7, "prob": 0.0}, {"actual": 3, "prob": 1.0}, {"actual": 2, "prob": 0.0}, {"actual": 1, "prob": 0.0}, {"actual": 3, "prob": 1.0}, {"actual": 2, "prob": 0.0}, {"actual": 8, "prob": 0.0}, {"actual": 0, "prob": 0.0}, {"actual": 3, "prob": 1.0}, {"actual": 6, "prob": 0.0}, {"actual": 4, "prob": 0.0}, {"actual": 3, "prob": 1.0}, {"actual": 1, "prob": 0.0}, {"actual": 5, "prob": 2.242130401594586e-30}, {"actual": 1, "prob": 0.0}, {"actual": 5, "prob": 2.726926811576094e-42}, {"actual": 3, "prob": 1.0}, {"actual": 3, "prob": 1.0}, {"actual": 0, "prob": 0.0}, {"actual": 4, "prob": 0.0}, {"actual": 4, "prob": 0.0}, {"actual": 4, "prob": 0.0}, {"actual": 9, "prob": 1.935643919454e-12}, {"actual": 0, "prob": 0.0}, {"actual": 8, "prob": 0.0}, {"actual": 1, "prob": 0.0}, {"actual": 3, "prob": 1.0}, {"actual": 9, "prob": 9.92460711594749e-15}, {"actual": 2, "prob": 0.0}, {"actual": 0, "prob": 0.0}, {"actual": 9, "prob": 4.660261759825701e-12}, {"actual": 9, "prob": 6.220759019015532e-08}, {"actual": 5, "prob": 1.4583006015720522e-18}, {"actual": 8, "prob": 0.0}, {"actual": 7, "prob": 0.0}, {"actual": 5, "prob": 0.0}, {"actual": 0, "prob": 0.0}, {"actual": 2, "prob": 0.0}, {"actual": 4, "prob": 0.0}, {"actual": 9, "prob": 2.342305630053179e-14}, {"actual": 5, "prob": 6.580826648682265e-20}, {"actual": 5, "prob": 0.0}, {"actual": 1, "prob": 0.0}, {"actual": 2, "prob": 0.0}, {"actual": 0, "prob": 0.0}, {"actual": 5, "prob": 0.0}, {"actual": 9, "prob": 1.148950400965687e-12}, {"actual": 6, "prob": 0.0}, {"actual": 1, "prob": 0.0}, {"actual": 5, "prob": 2.4288647321888112e-31}, {"actual": 6, "prob": 0.0}, {"actual": 1, "prob": 0.0}, {"actual": 8, "prob": 0.0}, {"actual": 1, "prob": 0.0}, {"actual": 1, "prob": 0.0}, {"actual": 0, "prob": 0.0}, {"actual": 4, "prob": 0.0}, {"actual": 7, "prob": 0.0}, {"actual": 7, "prob": 0.0}, {"actual": 8, "prob": 0.0}, {"actual": 1, "prob": 0.0}, {"actual": 0, "prob": 0.0}, {"actual": 9, "prob": 5.321872009744766e-08}, {"actual": 9, "prob": 2.112520020025599e-10}, {"actual": 2, "prob": 0.0}, {"actual": 4, "prob": 0.0}, {"actual": 1, "prob": 0.0}, {"actual": 9, "prob": 1.7586360969920611e-12}, {"actual": 1, "prob": 0.0}, {"actual": 9, "prob": 3.1569771796746693e-10}, {"actual": 8, "prob": 0.0}, {"actual": 1, "prob": 0.0}, {"actual": 8, "prob": 0.0}, {"actual": 4, "prob": 0.0}, {"actual": 4, "prob": 0.0}, {"actual": 4, "prob": 0.0}, {"actual": 6, "prob": 0.0}, {"actual": 9, "prob": 3.007376465913314e-12}, {"actual": 1, "prob": 0.0}, {"actual": 4, "prob": 0.0}, {"actual": 3, "prob": 1.0}, {"actual": 2, "prob": 0.0}, {"actual": 9, "prob": 5.558844400413432e-13}, {"actual": 1, "prob": 0.0}, {"actual": 2, "prob": 0.0}, {"actual": 8, "prob": 0.0}, {"actual": 7, "prob": 0.0}, {"actual": 5, "prob": 0.0}, {"actual": 4, "prob": 0.0}, {"actual": 5, "prob": 0.0}, {"actual": 1, "prob": 1.2737803040712587e-42}, {"actual": 6, "prob": 0.0}, {"actual": 5, "prob": 0.0}, {"actual": 2, "prob": 0.0}, {"actual": 9, "prob": 1.833917566418375e-12}]